{"accuracy": 0.92, "correct_count": 46, "total_count": 50}
{"id": "exec_parallel_12", "model_name": "gpt-4o-2024-11-20-FC", "test_category": "exec_parallel", "valid": false, "error": ["Could not find a matching function among index [0, 1, 2, 3] of model output for index 0 of possible answers.", {"Model Result Index 0": {"sub_error": ["Error in execution: \"estimate_derivative(function='3*x**2 + 2*x - 1',x=4)\". Error: 'int' object is not callable"], "sub_error_type": "executable_checker:execution_error", "model_executed_output": null}}, {"Model Result Index 1": {"sub_error": ["Error in execution: \"estimate_derivative(function='5*x**3 - 3*x**2 + 2*x + 1',x=-2)\". Error: 'int' object is not callable"], "sub_error_type": "executable_checker:execution_error", "model_executed_output": null}}, {"Model Result Index 2": {"sub_error": ["Error in execution: \"estimate_derivative(function='2*x**4 - 3*x**3 + 2*x**2 - x + 1',x=0)\". Error: 'int' object is not callable"], "sub_error_type": "executable_checker:execution_error", "model_executed_output": null}}, {"Model Result Index 3": {"sub_error": ["Error in execution: \"estimate_derivative(function='x**5 - 2*x**4 + 3*x**3 - 2*x**2 + x - 1',x=1)\". Error: 'int' object is not callable"], "sub_error_type": "executable_checker:execution_error", "model_executed_output": null}}], "error_type": "executable_checker:cannot_find_match", "prompt": {"id": "exec_parallel_12", "question": [[{"role": "user", "content": "I'm working on some calculus problems and need help estimating derivatives. Could you find the derivative of f(x) = 3x^2 + 2x - 1 at x = 4, calculate the derivative of g(x) = 5x^3 - 3x^2 + 2x + 1 at x = -2, determine the derivative of h(x) = 2x^4 - 3x^3 + 2x^2 - x + 1 at x = 0, and get the derivative of i(x) = x^5 - 2x^4 + 3x^3 - 2x^2 + x - 1 at x = 1?"}]], "function": [{"name": "estimate_derivative", "description": "Estimate the derivative of a function at a given point.", "parameters": {"type": "dict", "properties": {"function": {"type": "string", "description": "The function to calculate the derivative of."}, "x": {"type": "integer", "description": "The point to calculate the derivative at."}}, "required": ["function", "x"]}}], "execution_result": [26.000037678386434, 74.00004164992424, -1.000000082740371, 3.000000248221113], "execution_result_type": ["exact_match", "exact_match", "exact_match", "exact_match"]}, "model_result_raw": [{"estimate_derivative": "{\"function\": \"3*x**2 + 2*x - 1\", \"x\": 4}"}, {"estimate_derivative": "{\"function\": \"5*x**3 - 3*x**2 + 2*x + 1\", \"x\": -2}"}, {"estimate_derivative": "{\"function\": \"2*x**4 - 3*x**3 + 2*x**2 - x + 1\", \"x\": 0}"}, {"estimate_derivative": "{\"function\": \"x**5 - 2*x**4 + 3*x**3 - 2*x**2 + x - 1\", \"x\": 1}"}], "model_result_decoded": ["estimate_derivative(function='3*x**2 + 2*x - 1',x=4)", "estimate_derivative(function='5*x**3 - 3*x**2 + 2*x + 1',x=-2)", "estimate_derivative(function='2*x**4 - 3*x**3 + 2*x**2 - x + 1',x=0)", "estimate_derivative(function='x**5 - 2*x**4 + 3*x**3 - 2*x**2 + x - 1',x=1)"]}
{"id": "exec_parallel_15", "model_name": "gpt-4o-2024-11-20-FC", "test_category": "exec_parallel", "valid": false, "error": ["Could not find a matching function among index [2, 3] of model output for index 2 of possible answers.", {"Model Result Index 2": {"sub_error": ["Wrong execution result for \"get_active_covid_case_by_country(country='United States')\". Expected: {'get': 'statistics', 'parameters': {'country': 'United States'}, 'errors': [], 'results': 0, 'response': []}, but got: {'get': 'statistics', 'parameters': {'country': 'United States'}, 'errors': [], 'results': 0, 'response': []}. Type needs to be float or int for real time match criteria."], "sub_error_type": "executable_checker:wrong_result_real_time", "model_executed_output": {"get": "statistics", "parameters": {"country": "United States"}, "errors": [], "results": 0, "response": []}}}, {"Model Result Index 3": {"sub_error": ["Wrong execution result for \"get_active_covid_case_by_country(country='China')\". Expected: {'get': 'statistics', 'parameters': {'country': 'United States'}, 'errors': [], 'results': 0, 'response': []}, but got: 118977. Type needs to be float or int for real time match criteria."], "sub_error_type": "executable_checker:wrong_result_real_time", "model_executed_output": 118977}}], "error_type": "executable_checker:cannot_find_match", "prompt": {"id": "exec_parallel_15", "question": [[{"role": "user", "content": "With the pandemic still lingering, I'm trying to stay updated on the COVID-19 situation around the globe. I'm particularly interested in the current active case numbers for a few countries. Could you provide me with the latest figures for active COVID-19 cases in France, Italy, the United States, and China?"}]], "function": [{"name": "get_active_covid_case_by_country", "description": "Finds the most up to date active cases of a country result from COVID.", "parameters": {"type": "dict", "properties": {"country": {"type": "string", "description": "The country to find the active cases of, in the format of the country's full name."}}, "required": ["country"]}}], "execution_result": [0, 165544, {"get": "statistics", "parameters": {"country": "United States"}, "errors": [], "results": 0, "response": []}, 118977], "execution_result_type": ["real_time_match", "real_time_match", "real_time_match", "real_time_match"]}, "model_result_raw": [{"get_active_covid_case_by_country": "{\"country\": \"France\"}"}, {"get_active_covid_case_by_country": "{\"country\": \"Italy\"}"}, {"get_active_covid_case_by_country": "{\"country\": \"United States\"}"}, {"get_active_covid_case_by_country": "{\"country\": \"China\"}"}], "model_result_decoded": ["get_active_covid_case_by_country(country='France')", "get_active_covid_case_by_country(country='Italy')", "get_active_covid_case_by_country(country='United States')", "get_active_covid_case_by_country(country='China')"]}
{"id": "exec_parallel_16", "model_name": "gpt-4o-2024-11-20-FC", "test_category": "exec_parallel", "valid": false, "error": ["Could not find a matching function among index [0, 1, 2, 3] of model output for index 0 of possible answers.", {"Model Result Index 0": {"sub_error": ["Wrong execution result for \"get_company_name_by_stock_name(stock_name='AAPL')\". Expected: {'meta': {'version': 'v1.0', 'status': 200, 'copywrite': 'https://apicalls.io', 'symbol': 'AAPL', 'processedTime': '2025-03-27T02:33:50.703185Z'}, 'body': [{'shortname': 'Apple Inc.', 'quoteType': 'EQUITY', 'symbol': 'AAPL', 'index': 'quotes', 'score': 20317000, 'typeDisp': 'Equity', 'longname': 'Apple Inc.', 'exchDisp': 'NASDAQ', 'sector': 'Technology', 'sectorDisp': 'Technology', 'industry': 'Consumer Electronics', 'industryDisp': 'Consumer Electronics', 'dispSecIndFlag': True}, {'shortname': 'APPLE INC', 'quoteType': 'EQUITY', 'symbol': 'AAPL.MX', 'index': 'quotes', 'score': 20044, 'typeDisp': 'Equity', 'longname': 'Apple Inc.', 'exchDisp': 'Mexico', 'sector': 'Technology', 'sectorDisp': 'Technology', 'industry': 'Consumer Electronics', 'industryDisp': 'Consumer Electronics'}, {'shortname': 'Direxion Daily AAPL Bull 2X Sha', 'quoteType': 'ETF', 'symbol': 'AAPU', 'index': 'quotes', 'score': 20010, 'typeDisp': 'ETF', 'longname': 'Direxion Daily AAPL Bull 2X Shares', 'exchDisp': 'NASDAQ'}, {'shortname': 'AAPL Jan 2026 125.000 call', 'quoteType': 'OPTION', 'symbol': 'AAPL260116C00125000', 'index': 'quotes', 'score': 20004, 'typeDisp': 'Option', 'longname': 'AAPL Jan 2026 125.000 call', 'exchDisp': 'OPR'}, {'shortname': 'AAPL Jun 2026 140.000 call', 'quoteType': 'OPTION', 'symbol': 'AAPL260618C00140000', 'index': 'quotes', 'score': 20004, 'typeDisp': 'Option', 'longname': 'AAPL Jun 2026 140.000 call', 'exchDisp': 'OPR'}, {'shortname': 'AAPL Jun 2026 150.000 call', 'quoteType': 'OPTION', 'symbol': 'AAPL260618C00150000', 'index': 'quotes', 'score': 20004, 'typeDisp': 'Option', 'longname': 'AAPL Jun 2026 150.000 call', 'exchDisp': 'OPR'}, {'shortname': 'AAPL Jun 2026 220.000 call', 'quoteType': 'OPTION', 'symbol': 'AAPL260618C00220000', 'index': 'quotes', 'score': 20004, 'typeDisp': 'Option', 'longname': 'AAPL Jun 2026 220.000 call', 'exchDisp': 'OPR'}]}, but got: {'meta': {'version': 'v1.0', 'status': 200, 'copywrite': 'https://apicalls.io', 'symbol': 'AAPL', 'processedTime': '2025-03-27T02:35:12.858647Z'}, 'body': [{'shortname': 'Apple Inc.', 'quoteType': 'EQUITY', 'symbol': 'AAPL', 'index': 'quotes', 'score': 20317000, 'typeDisp': 'Equity', 'longname': 'Apple Inc.', 'exchDisp': 'NASDAQ', 'sector': 'Technology', 'sectorDisp': 'Technology', 'industry': 'Consumer Electronics', 'industryDisp': 'Consumer Electronics', 'dispSecIndFlag': True}, {'shortname': 'APPLE INC', 'quoteType': 'EQUITY', 'symbol': 'AAPL.MX', 'index': 'quotes', 'score': 20044, 'typeDisp': 'Equity', 'longname': 'Apple Inc.', 'exchDisp': 'Mexico', 'sector': 'Technology', 'sectorDisp': 'Technology', 'industry': 'Consumer Electronics', 'industryDisp': 'Consumer Electronics'}, {'shortname': 'Direxion Daily AAPL Bull 2X Sha', 'quoteType': 'ETF', 'symbol': 'AAPU', 'index': 'quotes', 'score': 20010, 'typeDisp': 'ETF', 'longname': 'Direxion Daily AAPL Bull 2X Shares', 'exchDisp': 'NASDAQ'}, {'shortname': 'AAPL Jun 2026 120.000 call', 'quoteType': 'OPTION', 'symbol': 'AAPL260618C00120000', 'index': 'quotes', 'score': 20004, 'typeDisp': 'Option', 'longname': 'AAPL Jun 2026 120.000 call', 'exchDisp': 'OPR'}, {'shortname': 'AAPL Jun 2026 220.000 call', 'quoteType': 'OPTION', 'symbol': 'AAPL260618C00220000', 'index': 'quotes', 'score': 20004, 'typeDisp': 'Option', 'longname': 'AAPL Jun 2026 220.000 call', 'exchDisp': 'OPR'}, {'shortname': 'AAPL Jun 2026 150.000 call', 'quoteType': 'OPTION', 'symbol': 'AAPL260618C00150000', 'index': 'quotes', 'score': 20004, 'typeDisp': 'Option', 'longname': 'AAPL Jun 2026 150.000 call', 'exchDisp': 'OPR'}, {'shortname': 'AAPL Jan 2026 125.000 call', 'quoteType': 'OPTION', 'symbol': 'AAPL260116C00125000', 'index': 'quotes', 'score': 20004, 'typeDisp': 'Option', 'longname': 'AAPL Jan 2026 125.000 call', 'exchDisp': 'OPR'}]}."], "sub_error_type": "executable_checker:wrong_result", "model_executed_output": {"meta": {"version": "v1.0", "status": 200, "copywrite": "https://apicalls.io", "symbol": "AAPL", "processedTime": "2025-03-27T02:35:12.858647Z"}, "body": [{"shortname": "Apple Inc.", "quoteType": "EQUITY", "symbol": "AAPL", "index": "quotes", "score": 20317000, "typeDisp": "Equity", "longname": "Apple Inc.", "exchDisp": "NASDAQ", "sector": "Technology", "sectorDisp": "Technology", "industry": "Consumer Electronics", "industryDisp": "Consumer Electronics", "dispSecIndFlag": true}, {"shortname": "APPLE INC", "quoteType": "EQUITY", "symbol": "AAPL.MX", "index": "quotes", "score": 20044, "typeDisp": "Equity", "longname": "Apple Inc.", "exchDisp": "Mexico", "sector": "Technology", "sectorDisp": "Technology", "industry": "Consumer Electronics", "industryDisp": "Consumer Electronics"}, {"shortname": "Direxion Daily AAPL Bull 2X Sha", "quoteType": "ETF", "symbol": "AAPU", "index": "quotes", "score": 20010, "typeDisp": "ETF", "longname": "Direxion Daily AAPL Bull 2X Shares", "exchDisp": "NASDAQ"}, {"shortname": "AAPL Jun 2026 120.000 call", "quoteType": "OPTION", "symbol": "AAPL260618C00120000", "index": "quotes", "score": 20004, "typeDisp": "Option", "longname": "AAPL Jun 2026 120.000 call", "exchDisp": "OPR"}, {"shortname": "AAPL Jun 2026 220.000 call", "quoteType": "OPTION", "symbol": "AAPL260618C00220000", "index": "quotes", "score": 20004, "typeDisp": "Option", "longname": "AAPL Jun 2026 220.000 call", "exchDisp": "OPR"}, {"shortname": "AAPL Jun 2026 150.000 call", "quoteType": "OPTION", "symbol": "AAPL260618C00150000", "index": "quotes", "score": 20004, "typeDisp": "Option", "longname": "AAPL Jun 2026 150.000 call", "exchDisp": "OPR"}, {"shortname": "AAPL Jan 2026 125.000 call", "quoteType": "OPTION", "symbol": "AAPL260116C00125000", "index": "quotes", "score": 20004, "typeDisp": "Option", "longname": "AAPL Jan 2026 125.000 call", "exchDisp": "OPR"}]}}}, {"Model Result Index 1": {"sub_error": ["Wrong execution result for \"get_company_name_by_stock_name(stock_name='GOOGL')\". Expected: {'meta': {'version': 'v1.0', 'status': 200, 'copywrite': 'https://apicalls.io', 'symbol': 'AAPL', 'processedTime': '2025-03-27T02:33:50.703185Z'}, 'body': [{'shortname': 'Apple Inc.', 'quoteType': 'EQUITY', 'symbol': 'AAPL', 'index': 'quotes', 'score': 20317000, 'typeDisp': 'Equity', 'longname': 'Apple Inc.', 'exchDisp': 'NASDAQ', 'sector': 'Technology', 'sectorDisp': 'Technology', 'industry': 'Consumer Electronics', 'industryDisp': 'Consumer Electronics', 'dispSecIndFlag': True}, {'shortname': 'APPLE INC', 'quoteType': 'EQUITY', 'symbol': 'AAPL.MX', 'index': 'quotes', 'score': 20044, 'typeDisp': 'Equity', 'longname': 'Apple Inc.', 'exchDisp': 'Mexico', 'sector': 'Technology', 'sectorDisp': 'Technology', 'industry': 'Consumer Electronics', 'industryDisp': 'Consumer Electronics'}, {'shortname': 'Direxion Daily AAPL Bull 2X Sha', 'quoteType': 'ETF', 'symbol': 'AAPU', 'index': 'quotes', 'score': 20010, 'typeDisp': 'ETF', 'longname': 'Direxion Daily AAPL Bull 2X Shares', 'exchDisp': 'NASDAQ'}, {'shortname': 'AAPL Jan 2026 125.000 call', 'quoteType': 'OPTION', 'symbol': 'AAPL260116C00125000', 'index': 'quotes', 'score': 20004, 'typeDisp': 'Option', 'longname': 'AAPL Jan 2026 125.000 call', 'exchDisp': 'OPR'}, {'shortname': 'AAPL Jun 2026 140.000 call', 'quoteType': 'OPTION', 'symbol': 'AAPL260618C00140000', 'index': 'quotes', 'score': 20004, 'typeDisp': 'Option', 'longname': 'AAPL Jun 2026 140.000 call', 'exchDisp': 'OPR'}, {'shortname': 'AAPL Jun 2026 150.000 call', 'quoteType': 'OPTION', 'symbol': 'AAPL260618C00150000', 'index': 'quotes', 'score': 20004, 'typeDisp': 'Option', 'longname': 'AAPL Jun 2026 150.000 call', 'exchDisp': 'OPR'}, {'shortname': 'AAPL Jun 2026 220.000 call', 'quoteType': 'OPTION', 'symbol': 'AAPL260618C00220000', 'index': 'quotes', 'score': 20004, 'typeDisp': 'Option', 'longname': 'AAPL Jun 2026 220.000 call', 'exchDisp': 'OPR'}]}, but got: {'meta': {'version': 'v1.0', 'status': 200, 'copywrite': 'https://apicalls.io', 'symbol': 'GOOGL', 'processedTime': '2025-03-27T02:35:13.601420Z'}, 'body': [{'shortname': 'Alphabet Inc.', 'quoteType': 'EQUITY', 'symbol': 'GOOGL', 'index': 'quotes', 'score': 10944500, 'typeDisp': 'Equity', 'longname': 'Alphabet Inc.', 'exchDisp': 'NASDAQ', 'sector': 'Communication Services', 'sectorDisp': 'Communication Services', 'industry': 'Internet Content & Information', 'industryDisp': 'Internet Content & Information', 'dispSecIndFlag': True}, {'shortname': 'ALPHABET INC', 'quoteType': 'EQUITY', 'symbol': 'GOOGL.MX', 'index': 'quotes', 'score': 20039, 'typeDisp': 'Equity', 'longname': 'Alphabet Inc.', 'exchDisp': 'Mexico', 'sector': 'Communication Services', 'sectorDisp': 'Communication Services', 'industry': 'Internet Content & Information', 'industryDisp': 'Internet Content & Information'}, {'shortname': 'GOOGL Jan 2026 170.000 call', 'quoteType': 'OPTION', 'symbol': 'GOOGL260116C00170000', 'index': 'quotes', 'score': 20007, 'typeDisp': 'Option', 'longname': 'GOOGL Jan 2026 170.000 call', 'exchDisp': 'OPR'}, {'shortname': 'Direxion Daily GOOGL Bull 2X Sh', 'quoteType': 'ETF', 'symbol': 'GGLL', 'index': 'quotes', 'score': 20005, 'typeDisp': 'ETF', 'longname': 'Direxion Daily GOOGL Bull 2X Shares', 'exchDisp': 'NASDAQ'}, {'shortname': 'GOOGL Jan 2026 100.000 put', 'quoteType': 'OPTION', 'symbol': 'GOOGL260116P00100000', 'index': 'quotes', 'score': 20005, 'typeDisp': 'Option', 'longname': 'GOOGL Jan 2026 100.000 put', 'exchDisp': 'OPR'}, {'shortname': 'GOOGL Jan 2026 165.000 put', 'quoteType': 'OPTION', 'symbol': 'GOOGL260116P00165000', 'index': 'quotes', 'score': 20005, 'typeDisp': 'Option', 'longname': 'GOOGL Jan 2026 165.000 put', 'exchDisp': 'OPR'}, {'shortname': 'GOOGL Dec 2025 200.000 call', 'quoteType': 'OPTION', 'symbol': 'GOOGL251219C00200000', 'index': 'quotes', 'score': 20005, 'typeDisp': 'Option', 'longname': 'GOOGL Dec 2025 200.000 call', 'exchDisp': 'OPR'}]}."], "sub_error_type": "executable_checker:wrong_result", "model_executed_output": {"meta": {"version": "v1.0", "status": 200, "copywrite": "https://apicalls.io", "symbol": "GOOGL", "processedTime": "2025-03-27T02:35:13.601420Z"}, "body": [{"shortname": "Alphabet Inc.", "quoteType": "EQUITY", "symbol": "GOOGL", "index": "quotes", "score": 10944500, "typeDisp": "Equity", "longname": "Alphabet Inc.", "exchDisp": "NASDAQ", "sector": "Communication Services", "sectorDisp": "Communication Services", "industry": "Internet Content & Information", "industryDisp": "Internet Content & Information", "dispSecIndFlag": true}, {"shortname": "ALPHABET INC", "quoteType": "EQUITY", "symbol": "GOOGL.MX", "index": "quotes", "score": 20039, "typeDisp": "Equity", "longname": "Alphabet Inc.", "exchDisp": "Mexico", "sector": "Communication Services", "sectorDisp": "Communication Services", "industry": "Internet Content & Information", "industryDisp": "Internet Content & Information"}, {"shortname": "GOOGL Jan 2026 170.000 call", "quoteType": "OPTION", "symbol": "GOOGL260116C00170000", "index": "quotes", "score": 20007, "typeDisp": "Option", "longname": "GOOGL Jan 2026 170.000 call", "exchDisp": "OPR"}, {"shortname": "Direxion Daily GOOGL Bull 2X Sh", "quoteType": "ETF", "symbol": "GGLL", "index": "quotes", "score": 20005, "typeDisp": "ETF", "longname": "Direxion Daily GOOGL Bull 2X Shares", "exchDisp": "NASDAQ"}, {"shortname": "GOOGL Jan 2026 100.000 put", "quoteType": "OPTION", "symbol": "GOOGL260116P00100000", "index": "quotes", "score": 20005, "typeDisp": "Option", "longname": "GOOGL Jan 2026 100.000 put", "exchDisp": "OPR"}, {"shortname": "GOOGL Jan 2026 165.000 put", "quoteType": "OPTION", "symbol": "GOOGL260116P00165000", "index": "quotes", "score": 20005, "typeDisp": "Option", "longname": "GOOGL Jan 2026 165.000 put", "exchDisp": "OPR"}, {"shortname": "GOOGL Dec 2025 200.000 call", "quoteType": "OPTION", "symbol": "GOOGL251219C00200000", "index": "quotes", "score": 20005, "typeDisp": "Option", "longname": "GOOGL Dec 2025 200.000 call", "exchDisp": "OPR"}]}}}, {"Model Result Index 2": {"sub_error": ["Wrong execution result for \"get_company_name_by_stock_name(stock_name='AMZN')\". Expected: {'meta': {'version': 'v1.0', 'status': 200, 'copywrite': 'https://apicalls.io', 'symbol': 'AAPL', 'processedTime': '2025-03-27T02:33:50.703185Z'}, 'body': [{'shortname': 'Apple Inc.', 'quoteType': 'EQUITY', 'symbol': 'AAPL', 'index': 'quotes', 'score': 20317000, 'typeDisp': 'Equity', 'longname': 'Apple Inc.', 'exchDisp': 'NASDAQ', 'sector': 'Technology', 'sectorDisp': 'Technology', 'industry': 'Consumer Electronics', 'industryDisp': 'Consumer Electronics', 'dispSecIndFlag': True}, {'shortname': 'APPLE INC', 'quoteType': 'EQUITY', 'symbol': 'AAPL.MX', 'index': 'quotes', 'score': 20044, 'typeDisp': 'Equity', 'longname': 'Apple Inc.', 'exchDisp': 'Mexico', 'sector': 'Technology', 'sectorDisp': 'Technology', 'industry': 'Consumer Electronics', 'industryDisp': 'Consumer Electronics'}, {'shortname': 'Direxion Daily AAPL Bull 2X Sha', 'quoteType': 'ETF', 'symbol': 'AAPU', 'index': 'quotes', 'score': 20010, 'typeDisp': 'ETF', 'longname': 'Direxion Daily AAPL Bull 2X Shares', 'exchDisp': 'NASDAQ'}, {'shortname': 'AAPL Jan 2026 125.000 call', 'quoteType': 'OPTION', 'symbol': 'AAPL260116C00125000', 'index': 'quotes', 'score': 20004, 'typeDisp': 'Option', 'longname': 'AAPL Jan 2026 125.000 call', 'exchDisp': 'OPR'}, {'shortname': 'AAPL Jun 2026 140.000 call', 'quoteType': 'OPTION', 'symbol': 'AAPL260618C00140000', 'index': 'quotes', 'score': 20004, 'typeDisp': 'Option', 'longname': 'AAPL Jun 2026 140.000 call', 'exchDisp': 'OPR'}, {'shortname': 'AAPL Jun 2026 150.000 call', 'quoteType': 'OPTION', 'symbol': 'AAPL260618C00150000', 'index': 'quotes', 'score': 20004, 'typeDisp': 'Option', 'longname': 'AAPL Jun 2026 150.000 call', 'exchDisp': 'OPR'}, {'shortname': 'AAPL Jun 2026 220.000 call', 'quoteType': 'OPTION', 'symbol': 'AAPL260618C00220000', 'index': 'quotes', 'score': 20004, 'typeDisp': 'Option', 'longname': 'AAPL Jun 2026 220.000 call', 'exchDisp': 'OPR'}]}, but got: {'meta': {'version': 'v1.0', 'status': 200, 'copywrite': 'https://apicalls.io', 'symbol': 'AMZN', 'processedTime': '2025-03-27T02:35:14.319525Z'}, 'body': [{'shortname': 'Amazon.com, Inc.', 'quoteType': 'EQUITY', 'symbol': 'AMZN', 'index': 'quotes', 'score': 14774000, 'typeDisp': 'Equity', 'longname': 'Amazon.com, Inc.', 'exchDisp': 'NASDAQ', 'sector': 'Consumer Cyclical', 'sectorDisp': 'Consumer Cyclical', 'industry': 'Internet Retail', 'industryDisp': 'Internet Retail', 'dispSecIndFlag': True}, {'shortname': 'AMAZON COM INC', 'quoteType': 'EQUITY', 'symbol': 'AMZN.MX', 'index': 'quotes', 'score': 20047, 'typeDisp': 'Equity', 'longname': 'Amazon.com, Inc.', 'exchDisp': 'Mexico', 'sector': 'Consumer Cyclical', 'sectorDisp': 'Consumer Cyclical', 'industry': 'Internet Retail', 'industryDisp': 'Internet Retail'}, {'shortname': 'Direxion Daily AMZN Bull 2X Sha', 'quoteType': 'ETF', 'symbol': 'AMZU', 'index': 'quotes', 'score': 20011, 'typeDisp': 'ETF', 'longname': 'Direxion Daily AMZN Bull 2X Shares', 'exchDisp': 'NASDAQ'}, {'shortname': 'Tidal ETF Trust II YieldMax AMZ', 'quoteType': 'ETF', 'symbol': 'AMZY', 'index': 'quotes', 'score': 20008, 'typeDisp': 'ETF', 'longname': 'YieldMax AMZN Option Income Strategy ETF', 'exchDisp': 'NYSEArca'}, {'shortname': 'AMAZON (AMZN) YIELD SHARES PURP', 'quoteType': 'ETF', 'symbol': 'YAMZ.NE', 'index': 'quotes', 'score': 20004, 'typeDisp': 'ETF', 'longname': 'Amazon (AMZN) Yield Shares Purpose ETF', 'exchDisp': 'NEO'}, {'shortname': 'AMZN Jan 2026 220.000 call', 'quoteType': 'OPTION', 'symbol': 'AMZN260116C00220000', 'index': 'quotes', 'score': 20004, 'typeDisp': 'Option', 'longname': 'AMZN Jan 2026 220.000 call', 'exchDisp': 'OPR'}, {'shortname': 'AMZN Jan 2026 115.000 put', 'quoteType': 'OPTION', 'symbol': 'AMZN260116P00115000', 'index': 'quotes', 'score': 20004, 'typeDisp': 'Option', 'longname': 'AMZN Jan 2026 115.000 put', 'exchDisp': 'OPR'}]}."], "sub_error_type": "executable_checker:wrong_result", "model_executed_output": {"meta": {"version": "v1.0", "status": 200, "copywrite": "https://apicalls.io", "symbol": "AMZN", "processedTime": "2025-03-27T02:35:14.319525Z"}, "body": [{"shortname": "Amazon.com, Inc.", "quoteType": "EQUITY", "symbol": "AMZN", "index": "quotes", "score": 14774000, "typeDisp": "Equity", "longname": "Amazon.com, Inc.", "exchDisp": "NASDAQ", "sector": "Consumer Cyclical", "sectorDisp": "Consumer Cyclical", "industry": "Internet Retail", "industryDisp": "Internet Retail", "dispSecIndFlag": true}, {"shortname": "AMAZON COM INC", "quoteType": "EQUITY", "symbol": "AMZN.MX", "index": "quotes", "score": 20047, "typeDisp": "Equity", "longname": "Amazon.com, Inc.", "exchDisp": "Mexico", "sector": "Consumer Cyclical", "sectorDisp": "Consumer Cyclical", "industry": "Internet Retail", "industryDisp": "Internet Retail"}, {"shortname": "Direxion Daily AMZN Bull 2X Sha", "quoteType": "ETF", "symbol": "AMZU", "index": "quotes", "score": 20011, "typeDisp": "ETF", "longname": "Direxion Daily AMZN Bull 2X Shares", "exchDisp": "NASDAQ"}, {"shortname": "Tidal ETF Trust II YieldMax AMZ", "quoteType": "ETF", "symbol": "AMZY", "index": "quotes", "score": 20008, "typeDisp": "ETF", "longname": "YieldMax AMZN Option Income Strategy ETF", "exchDisp": "NYSEArca"}, {"shortname": "AMAZON (AMZN) YIELD SHARES PURP", "quoteType": "ETF", "symbol": "YAMZ.NE", "index": "quotes", "score": 20004, "typeDisp": "ETF", "longname": "Amazon (AMZN) Yield Shares Purpose ETF", "exchDisp": "NEO"}, {"shortname": "AMZN Jan 2026 220.000 call", "quoteType": "OPTION", "symbol": "AMZN260116C00220000", "index": "quotes", "score": 20004, "typeDisp": "Option", "longname": "AMZN Jan 2026 220.000 call", "exchDisp": "OPR"}, {"shortname": "AMZN Jan 2026 115.000 put", "quoteType": "OPTION", "symbol": "AMZN260116P00115000", "index": "quotes", "score": 20004, "typeDisp": "Option", "longname": "AMZN Jan 2026 115.000 put", "exchDisp": "OPR"}]}}}, {"Model Result Index 3": {"sub_error": ["Wrong execution result for \"get_company_name_by_stock_name(stock_name='MSFT')\". Expected: {'meta': {'version': 'v1.0', 'status': 200, 'copywrite': 'https://apicalls.io', 'symbol': 'AAPL', 'processedTime': '2025-03-27T02:33:50.703185Z'}, 'body': [{'shortname': 'Apple Inc.', 'quoteType': 'EQUITY', 'symbol': 'AAPL', 'index': 'quotes', 'score': 20317000, 'typeDisp': 'Equity', 'longname': 'Apple Inc.', 'exchDisp': 'NASDAQ', 'sector': 'Technology', 'sectorDisp': 'Technology', 'industry': 'Consumer Electronics', 'industryDisp': 'Consumer Electronics', 'dispSecIndFlag': True}, {'shortname': 'APPLE INC', 'quoteType': 'EQUITY', 'symbol': 'AAPL.MX', 'index': 'quotes', 'score': 20044, 'typeDisp': 'Equity', 'longname': 'Apple Inc.', 'exchDisp': 'Mexico', 'sector': 'Technology', 'sectorDisp': 'Technology', 'industry': 'Consumer Electronics', 'industryDisp': 'Consumer Electronics'}, {'shortname': 'Direxion Daily AAPL Bull 2X Sha', 'quoteType': 'ETF', 'symbol': 'AAPU', 'index': 'quotes', 'score': 20010, 'typeDisp': 'ETF', 'longname': 'Direxion Daily AAPL Bull 2X Shares', 'exchDisp': 'NASDAQ'}, {'shortname': 'AAPL Jan 2026 125.000 call', 'quoteType': 'OPTION', 'symbol': 'AAPL260116C00125000', 'index': 'quotes', 'score': 20004, 'typeDisp': 'Option', 'longname': 'AAPL Jan 2026 125.000 call', 'exchDisp': 'OPR'}, {'shortname': 'AAPL Jun 2026 140.000 call', 'quoteType': 'OPTION', 'symbol': 'AAPL260618C00140000', 'index': 'quotes', 'score': 20004, 'typeDisp': 'Option', 'longname': 'AAPL Jun 2026 140.000 call', 'exchDisp': 'OPR'}, {'shortname': 'AAPL Jun 2026 150.000 call', 'quoteType': 'OPTION', 'symbol': 'AAPL260618C00150000', 'index': 'quotes', 'score': 20004, 'typeDisp': 'Option', 'longname': 'AAPL Jun 2026 150.000 call', 'exchDisp': 'OPR'}, {'shortname': 'AAPL Jun 2026 220.000 call', 'quoteType': 'OPTION', 'symbol': 'AAPL260618C00220000', 'index': 'quotes', 'score': 20004, 'typeDisp': 'Option', 'longname': 'AAPL Jun 2026 220.000 call', 'exchDisp': 'OPR'}]}, but got: {'meta': {'version': 'v1.0', 'status': 200, 'copywrite': 'https://apicalls.io', 'symbol': 'MSFT', 'processedTime': '2025-03-27T02:35:15.064262Z'}, 'body': [{'shortname': 'Microsoft Corporation', 'quoteType': 'EQUITY', 'symbol': 'MSFT', 'index': 'quotes', 'score': 13958000, 'typeDisp': 'Equity', 'longname': 'Microsoft Corporation', 'exchDisp': 'NASDAQ', 'sector': 'Technology', 'sectorDisp': 'Technology', 'industry': 'Software\u2014Infrastructure', 'industryDisp': 'Software\u2014Infrastructure', 'dispSecIndFlag': True}, {'shortname': 'MICROSOFT CORP', 'quoteType': 'EQUITY', 'symbol': 'MSFT.MX', 'index': 'quotes', 'score': 20037, 'typeDisp': 'Equity', 'longname': 'Microsoft Corporation', 'exchDisp': 'Mexico', 'sector': 'Technology', 'sectorDisp': 'Technology', 'industry': 'Software\u2014Infrastructure', 'industryDisp': 'Software\u2014Infrastructure'}, {'shortname': 'Direxion Daily MSFT Bull 2X Sha', 'quoteType': 'ETF', 'symbol': 'MSFU', 'index': 'quotes', 'score': 20011, 'typeDisp': 'ETF', 'longname': 'Direxion Daily MSFT Bull 2X Shares', 'exchDisp': 'NASDAQ'}, {'shortname': 'MSFT Dec 2025 270.000 put', 'quoteType': 'OPTION', 'symbol': 'MSFT251219P00270000', 'index': 'quotes', 'score': 20005, 'typeDisp': 'Option', 'longname': 'MSFT Dec 2025 270.000 put', 'exchDisp': 'OPR'}, {'shortname': 'MSFT Jan 2026 380.000 call', 'quoteType': 'OPTION', 'symbol': 'MSFT260116C00380000', 'index': 'quotes', 'score': 20005, 'typeDisp': 'Option', 'longname': 'MSFT Jan 2026 380.000 call', 'exchDisp': 'OPR'}, {'shortname': 'MSFT Dec 2025 200.000 put', 'quoteType': 'OPTION', 'symbol': 'MSFT251219P00200000', 'index': 'quotes', 'score': 20005, 'typeDisp': 'Option', 'longname': 'MSFT Dec 2025 200.000 put', 'exchDisp': 'OPR'}, {'shortname': 'MSFT Dec 2025 535.000 call', 'quoteType': 'OPTION', 'symbol': 'MSFT251219C00535000', 'index': 'quotes', 'score': 20004, 'typeDisp': 'Option', 'longname': 'MSFT Dec 2025 535.000 call', 'exchDisp': 'OPR'}]}."], "sub_error_type": "executable_checker:wrong_result", "model_executed_output": {"meta": {"version": "v1.0", "status": 200, "copywrite": "https://apicalls.io", "symbol": "MSFT", "processedTime": "2025-03-27T02:35:15.064262Z"}, "body": [{"shortname": "Microsoft Corporation", "quoteType": "EQUITY", "symbol": "MSFT", "index": "quotes", "score": 13958000, "typeDisp": "Equity", "longname": "Microsoft Corporation", "exchDisp": "NASDAQ", "sector": "Technology", "sectorDisp": "Technology", "industry": "Software\u2014Infrastructure", "industryDisp": "Software\u2014Infrastructure", "dispSecIndFlag": true}, {"shortname": "MICROSOFT CORP", "quoteType": "EQUITY", "symbol": "MSFT.MX", "index": "quotes", "score": 20037, "typeDisp": "Equity", "longname": "Microsoft Corporation", "exchDisp": "Mexico", "sector": "Technology", "sectorDisp": "Technology", "industry": "Software\u2014Infrastructure", "industryDisp": "Software\u2014Infrastructure"}, {"shortname": "Direxion Daily MSFT Bull 2X Sha", "quoteType": "ETF", "symbol": "MSFU", "index": "quotes", "score": 20011, "typeDisp": "ETF", "longname": "Direxion Daily MSFT Bull 2X Shares", "exchDisp": "NASDAQ"}, {"shortname": "MSFT Dec 2025 270.000 put", "quoteType": "OPTION", "symbol": "MSFT251219P00270000", "index": "quotes", "score": 20005, "typeDisp": "Option", "longname": "MSFT Dec 2025 270.000 put", "exchDisp": "OPR"}, {"shortname": "MSFT Jan 2026 380.000 call", "quoteType": "OPTION", "symbol": "MSFT260116C00380000", "index": "quotes", "score": 20005, "typeDisp": "Option", "longname": "MSFT Jan 2026 380.000 call", "exchDisp": "OPR"}, {"shortname": "MSFT Dec 2025 200.000 put", "quoteType": "OPTION", "symbol": "MSFT251219P00200000", "index": "quotes", "score": 20005, "typeDisp": "Option", "longname": "MSFT Dec 2025 200.000 put", "exchDisp": "OPR"}, {"shortname": "MSFT Dec 2025 535.000 call", "quoteType": "OPTION", "symbol": "MSFT251219C00535000", "index": "quotes", "score": 20004, "typeDisp": "Option", "longname": "MSFT Dec 2025 535.000 call", "exchDisp": "OPR"}]}}}], "error_type": "executable_checker:cannot_find_match", "prompt": {"id": "exec_parallel_16", "question": [[{"role": "user", "content": "I'm currently analyzing the stocks with symbols 'AAPL', 'GOOGL', 'AMZN', and 'MSFT' for my financial report and need to match them with their corresponding companies. Can you provide me with the company names for these stocks?"}]], "function": [{"name": "get_company_name_by_stock_name", "description": "Finds the company name of a stock by its stock name.", "parameters": {"type": "dict", "properties": {"stock_name": {"type": "string", "description": "The stock name of the product, in the format of the stock symbol."}}, "required": ["stock_name"]}}], "execution_result": [{"meta": {"version": "v1.0", "status": 200, "copywrite": "https://apicalls.io", "symbol": "AAPL", "processedTime": "2025-03-27T02:33:50.703185Z"}, "body": [{"shortname": "Apple Inc.", "quoteType": "EQUITY", "symbol": "AAPL", "index": "quotes", "score": 20317000, "typeDisp": "Equity", "longname": "Apple Inc.", "exchDisp": "NASDAQ", "sector": "Technology", "sectorDisp": "Technology", "industry": "Consumer Electronics", "industryDisp": "Consumer Electronics", "dispSecIndFlag": true}, {"shortname": "APPLE INC", "quoteType": "EQUITY", "symbol": "AAPL.MX", "index": "quotes", "score": 20044, "typeDisp": "Equity", "longname": "Apple Inc.", "exchDisp": "Mexico", "sector": "Technology", "sectorDisp": "Technology", "industry": "Consumer Electronics", "industryDisp": "Consumer Electronics"}, {"shortname": "Direxion Daily AAPL Bull 2X Sha", "quoteType": "ETF", "symbol": "AAPU", "index": "quotes", "score": 20010, "typeDisp": "ETF", "longname": "Direxion Daily AAPL Bull 2X Shares", "exchDisp": "NASDAQ"}, {"shortname": "AAPL Jan 2026 125.000 call", "quoteType": "OPTION", "symbol": "AAPL260116C00125000", "index": "quotes", "score": 20004, "typeDisp": "Option", "longname": "AAPL Jan 2026 125.000 call", "exchDisp": "OPR"}, {"shortname": "AAPL Jun 2026 140.000 call", "quoteType": "OPTION", "symbol": "AAPL260618C00140000", "index": "quotes", "score": 20004, "typeDisp": "Option", "longname": "AAPL Jun 2026 140.000 call", "exchDisp": "OPR"}, {"shortname": "AAPL Jun 2026 150.000 call", "quoteType": "OPTION", "symbol": "AAPL260618C00150000", "index": "quotes", "score": 20004, "typeDisp": "Option", "longname": "AAPL Jun 2026 150.000 call", "exchDisp": "OPR"}, {"shortname": "AAPL Jun 2026 220.000 call", "quoteType": "OPTION", "symbol": "AAPL260618C00220000", "index": "quotes", "score": 20004, "typeDisp": "Option", "longname": "AAPL Jun 2026 220.000 call", "exchDisp": "OPR"}]}, {"meta": {"version": "v1.0", "status": 200, "copywrite": "https://apicalls.io", "symbol": "GOOGL", "processedTime": "2025-03-27T02:33:51.465207Z"}, "body": [{"shortname": "Alphabet Inc.", "quoteType": "EQUITY", "symbol": "GOOGL", "index": "quotes", "score": 10944500, "typeDisp": "Equity", "longname": "Alphabet Inc.", "exchDisp": "NASDAQ", "sector": "Communication Services", "sectorDisp": "Communication Services", "industry": "Internet Content & Information", "industryDisp": "Internet Content & Information", "dispSecIndFlag": true}, {"shortname": "ALPHABET INC", "quoteType": "EQUITY", "symbol": "GOOGL.MX", "index": "quotes", "score": 20039, "typeDisp": "Equity", "longname": "Alphabet Inc.", "exchDisp": "Mexico", "sector": "Communication Services", "sectorDisp": "Communication Services", "industry": "Internet Content & Information", "industryDisp": "Internet Content & Information"}, {"shortname": "GOOGL Jan 2026 170.000 call", "quoteType": "OPTION", "symbol": "GOOGL260116C00170000", "index": "quotes", "score": 20007, "typeDisp": "Option", "longname": "GOOGL Jan 2026 170.000 call", "exchDisp": "OPR"}, {"shortname": "Direxion Daily GOOGL Bull 2X Sh", "quoteType": "ETF", "symbol": "GGLL", "index": "quotes", "score": 20005, "typeDisp": "ETF", "longname": "Direxion Daily GOOGL Bull 2X Shares", "exchDisp": "NASDAQ"}, {"shortname": "GOOGL Jan 2026 100.000 put", "quoteType": "OPTION", "symbol": "GOOGL260116P00100000", "index": "quotes", "score": 20005, "typeDisp": "Option", "longname": "GOOGL Jan 2026 100.000 put", "exchDisp": "OPR"}, {"shortname": "GOOGL Jan 2026 165.000 put", "quoteType": "OPTION", "symbol": "GOOGL260116P00165000", "index": "quotes", "score": 20005, "typeDisp": "Option", "longname": "GOOGL Jan 2026 165.000 put", "exchDisp": "OPR"}, {"shortname": "GOOGL Dec 2025 200.000 call", "quoteType": "OPTION", "symbol": "GOOGL251219C00200000", "index": "quotes", "score": 20005, "typeDisp": "Option", "longname": "GOOGL Dec 2025 200.000 call", "exchDisp": "OPR"}]}, {"meta": {"version": "v1.0", "status": 200, "copywrite": "https://apicalls.io", "symbol": "AMZN", "processedTime": "2025-03-27T02:33:52.208119Z"}, "body": [{"shortname": "Amazon.com, Inc.", "quoteType": "EQUITY", "symbol": "AMZN", "index": "quotes", "score": 14774000, "typeDisp": "Equity", "longname": "Amazon.com, Inc.", "exchDisp": "NASDAQ", "sector": "Consumer Cyclical", "sectorDisp": "Consumer Cyclical", "industry": "Internet Retail", "industryDisp": "Internet Retail", "dispSecIndFlag": true}, {"shortname": "AMAZON COM INC", "quoteType": "EQUITY", "symbol": "AMZN.MX", "index": "quotes", "score": 20047, "typeDisp": "Equity", "longname": "Amazon.com, Inc.", "exchDisp": "Mexico", "sector": "Consumer Cyclical", "sectorDisp": "Consumer Cyclical", "industry": "Internet Retail", "industryDisp": "Internet Retail"}, {"shortname": "Direxion Daily AMZN Bull 2X Sha", "quoteType": "ETF", "symbol": "AMZU", "index": "quotes", "score": 20011, "typeDisp": "ETF", "longname": "Direxion Daily AMZN Bull 2X Shares", "exchDisp": "NASDAQ"}, {"shortname": "Tidal ETF Trust II YieldMax AMZ", "quoteType": "ETF", "symbol": "AMZY", "index": "quotes", "score": 20008, "typeDisp": "ETF", "longname": "YieldMax AMZN Option Income Strategy ETF", "exchDisp": "NYSEArca"}, {"shortname": "AMAZON (AMZN) YIELD SHARES PURP", "quoteType": "ETF", "symbol": "YAMZ.NE", "index": "quotes", "score": 20004, "typeDisp": "ETF", "longname": "Amazon (AMZN) Yield Shares Purpose ETF", "exchDisp": "NEO"}, {"shortname": "AMZN Jun 2026 120.000 call", "quoteType": "OPTION", "symbol": "AMZN260618C00120000", "index": "quotes", "score": 20004, "typeDisp": "Option", "longname": "AMZN Jun 2026 120.000 call", "exchDisp": "OPR"}, {"shortname": "AMZN Jun 2025 160.000 call", "quoteType": "OPTION", "symbol": "AMZN250620C00160000", "index": "quotes", "score": 20004, "typeDisp": "Option", "longname": "AMZN Jun 2025 160.000 call", "exchDisp": "OPR"}]}, {"meta": {"version": "v1.0", "status": 200, "copywrite": "https://apicalls.io", "symbol": "MSFT", "processedTime": "2025-03-27T02:33:53.060225Z"}, "body": [{"shortname": "Microsoft Corporation", "quoteType": "EQUITY", "symbol": "MSFT", "index": "quotes", "score": 13958000, "typeDisp": "Equity", "longname": "Microsoft Corporation", "exchDisp": "NASDAQ", "sector": "Technology", "sectorDisp": "Technology", "industry": "Software\u2014Infrastructure", "industryDisp": "Software\u2014Infrastructure", "dispSecIndFlag": true}, {"shortname": "MICROSOFT CORP", "quoteType": "EQUITY", "symbol": "MSFT.MX", "index": "quotes", "score": 20037, "typeDisp": "Equity", "longname": "Microsoft Corporation", "exchDisp": "Mexico", "sector": "Technology", "sectorDisp": "Technology", "industry": "Software\u2014Infrastructure", "industryDisp": "Software\u2014Infrastructure"}, {"shortname": "Direxion Daily MSFT Bull 2X Sha", "quoteType": "ETF", "symbol": "MSFU", "index": "quotes", "score": 20011, "typeDisp": "ETF", "longname": "Direxion Daily MSFT Bull 2X Shares", "exchDisp": "NASDAQ"}, {"shortname": "MSFT Jan 2026 380.000 call", "quoteType": "OPTION", "symbol": "MSFT260116C00380000", "index": "quotes", "score": 20005, "typeDisp": "Option", "longname": "MSFT Jan 2026 380.000 call", "exchDisp": "OPR"}, {"shortname": "MSFT Dec 2025 270.000 put", "quoteType": "OPTION", "symbol": "MSFT251219P00270000", "index": "quotes", "score": 20005, "typeDisp": "Option", "longname": "MSFT Dec 2025 270.000 put", "exchDisp": "OPR"}, {"shortname": "MSFT Dec 2025 200.000 put", "quoteType": "OPTION", "symbol": "MSFT251219P00200000", "index": "quotes", "score": 20005, "typeDisp": "Option", "longname": "MSFT Dec 2025 200.000 put", "exchDisp": "OPR"}, {"shortname": "MSFT Dec 2025 535.000 call", "quoteType": "OPTION", "symbol": "MSFT251219C00535000", "index": "quotes", "score": 20004, "typeDisp": "Option", "longname": "MSFT Dec 2025 535.000 call", "exchDisp": "OPR"}]}], "execution_result_type": ["exact_match", "exact_match", "exact_match", "exact_match"]}, "model_result_raw": [{"get_company_name_by_stock_name": "{\"stock_name\": \"AAPL\"}"}, {"get_company_name_by_stock_name": "{\"stock_name\": \"GOOGL\"}"}, {"get_company_name_by_stock_name": "{\"stock_name\": \"AMZN\"}"}, {"get_company_name_by_stock_name": "{\"stock_name\": \"MSFT\"}"}], "model_result_decoded": ["get_company_name_by_stock_name(stock_name='AAPL')", "get_company_name_by_stock_name(stock_name='GOOGL')", "get_company_name_by_stock_name(stock_name='AMZN')", "get_company_name_by_stock_name(stock_name='MSFT')"]}
{"id": "exec_parallel_44", "model_name": "gpt-4o-2024-11-20-FC", "test_category": "exec_parallel", "valid": false, "error": ["Could not find a matching function among index [2, 3] of model output for index 2 of possible answers.", {"Model Result Index 2": {"sub_error": ["Wrong execution result for \"calculate_nutritional_needs(weight=85,height=175,age=40,gender='male',activity_level=4,goal='lose')\". Expected: {'calories': 2995.7188000000006, 'proteins_g': 224.67891000000003, 'fats_g': 83.21441111111113, 'carbohydrates_g': 337.0183650000001}, but got: {'calories': 2673.7447000000006, 'proteins_g': 200.53085250000004, 'fats_g': 74.27068611111113, 'carbohydrates_g': 300.79627875000006}."], "sub_error_type": "executable_checker:wrong_result", "model_executed_output": {"calories": 2673.7447000000006, "proteins_g": 200.53085250000004, "fats_g": 74.27068611111113, "carbohydrates_g": 300.79627875000006}}}, {"Model Result Index 3": {"sub_error": ["Wrong execution result for \"calculate_nutritional_needs(weight=70,height=160,age=55,gender='female',activity_level=1,goal='lose')\". Expected: {'calories': 2995.7188000000006, 'proteins_g': 224.67891000000003, 'fats_g': 83.21441111111113, 'carbohydrates_g': 337.0183650000001}, but got: {'calories': 1122.8956, 'proteins_g': 84.21717, 'fats_g': 31.191544444444446, 'carbohydrates_g': 126.32575500000002}."], "sub_error_type": "executable_checker:wrong_result", "model_executed_output": {"calories": 1122.8956, "proteins_g": 84.21717, "fats_g": 31.191544444444446, "carbohydrates_g": 126.32575500000002}}}], "error_type": "executable_checker:cannot_find_match", "prompt": {"id": "exec_parallel_44", "question": [[{"role": "user", "content": "I'm working on a new fitness plan and need to tailor it specifically for a few clients with different profiles. Could you help me calculate the daily nutritional needs for a 25-year-old male (180 cm, 75 kg, moderately active, weight gain), a 30-year-old female (165 cm, 65 kg, lightly active, weight maintenance), a 40-year-old male (175 cm, 85 kg, very active, weight loss), and a 55-year-old female (160 cm, 70 kg, not very active, weight loss)?"}]], "function": [{"name": "calculate_nutritional_needs", "description": "Calculates the nutritional needs of a person based on their weight, height, age, gender, activity level, and goal.", "parameters": {"type": "dict", "properties": {"weight": {"type": "float", "description": "The weight of the person in kilograms."}, "height": {"type": "float", "description": "The height of the person in centimeters."}, "age": {"type": "float", "description": "The age of the person in years."}, "gender": {"type": "string", "description": "The gender of the person. Possible options [male, female, other]."}, "activity_level": {"type": "float", "description": "The activity level of the person. Possible options [1,2,3,4,5]."}, "goal": {"type": "string", "description": "The goal of the person. Possible options [lose, gain, maintain]."}}, "required": ["weight", "height", "age", "gender", "activity_level", "goal"]}}], "execution_result": [{"calories": 3313.2996, "proteins_g": 248.49746999999996, "fats_g": 92.03609999999999, "carbohydrates_g": 372.746205}, {"calories": 1966.1372499999995, "proteins_g": 147.46029374999995, "fats_g": 54.614923611111095, "carbohydrates_g": 221.19044062499995}, {"calories": 2995.7188000000006, "proteins_g": 224.67891000000003, "fats_g": 83.21441111111113, "carbohydrates_g": 337.0183650000001}, {"calories": 1122.8956, "proteins_g": 84.21717, "fats_g": 31.191544444444446, "carbohydrates_g": 126.32575500000002}], "execution_result_type": ["exact_match", "exact_match", "exact_match", "exact_match"]}, "model_result_raw": [{"calculate_nutritional_needs": "{\"weight\": 75, \"height\": 180, \"age\": 25, \"gender\": \"male\", \"activity_level\": 3, \"goal\": \"gain\"}"}, {"calculate_nutritional_needs": "{\"weight\": 65, \"height\": 165, \"age\": 30, \"gender\": \"female\", \"activity_level\": 2, \"goal\": \"maintain\"}"}, {"calculate_nutritional_needs": "{\"weight\": 85, \"height\": 175, \"age\": 40, \"gender\": \"male\", \"activity_level\": 4, \"goal\": \"lose\"}"}, {"calculate_nutritional_needs": "{\"weight\": 70, \"height\": 160, \"age\": 55, \"gender\": \"female\", \"activity_level\": 1, \"goal\": \"lose\"}"}], "model_result_decoded": ["calculate_nutritional_needs(weight=75,height=180,age=25,gender='male',activity_level=3,goal='gain')", "calculate_nutritional_needs(weight=65,height=165,age=30,gender='female',activity_level=2,goal='maintain')", "calculate_nutritional_needs(weight=85,height=175,age=40,gender='male',activity_level=4,goal='lose')", "calculate_nutritional_needs(weight=70,height=160,age=55,gender='female',activity_level=1,goal='lose')"]}